{
  "id": "box_drawing",
  "name": { "th": "เส้นกรอบ", "en": "Box Drawing" },
  "data": [
    { "api": "U+2500", "text": "─", "name": { "th": "เส้นนอนบาง", "en": "Box Drawings Light Horizontal" } },
    { "api": "U+2501", "text": "━", "name": { "th": "เส้นนอนหนา", "en": "Box Drawings Heavy Horizontal" } },
    { "api": "U+2502", "text": "│", "name": { "th": "เส้นตั้งบาง", "en": "Box Drawings Light Vertical" } },
    { "api": "U+2503", "text": "┃", "name": { "th": "เส้นตั้งหนา", "en": "Box Drawings Heavy Vertical" } },
    { "api": "U+2504", "text": "┄", "name": { "th": "เส้นนอนประสามส่วน", "en": "Box Drawings Light Triple Dash Horizontal" } },
    { "api": "U+2505", "text": "┅", "name": { "th": "เส้นนอนประสามส่วนหนา", "en": "Box Drawings Heavy Triple Dash Horizontal" } },
    { "api": "U+2506", "text": "┆", "name": { "th": "เส้นตั้งประสามส่วน", "en": "Box Drawings Light Triple Dash Vertical" } },
    { "api": "U+2507", "text": "┇", "name": { "th": "เส้นตั้งประสามส่วนหนา", "en": "Box Drawings Heavy Triple Dash Vertical" } },
    { "api": "U+2508", "text": "┈", "name": { "th": "เส้นนอนประสี่ส่วน", "en": "Box Drawings Light Quadruple Dash Horizontal" } },
    { "api": "U+2509", "text": "┉", "name": { "th": "เส้นนอนประสี่ส่วนหนา", "en": "Box Drawings Heavy Quadruple Dash Horizontal" } },
    { "api": "U+250A", "text": "┊", "name": { "th": "เส้นตั้งประสี่ส่วน", "en": "Box Drawings Light Quadruple Dash Vertical" } },
    { "api": "U+250B", "text": "┋", "name": { "th": "เส้นตั้งประสี่ส่วนหนา", "en": "Box Drawings Heavy Quadruple Dash Vertical" } },
    { "api": "U+250C", "text": "┌", "name": { "th": "มุมบนซ้าย (บาง)", "en": "Box Drawings Light Down and Right" } },
    { "api": "U+250D", "text": "┍", "name": { "th": "มุมบนซ้าย (นอนหนา)", "en": "Box Drawings Down Light and Right Heavy" } },
    { "api": "U+250E", "text": "┎", "name": { "th": "มุมบนซ้าย (ตั้งหนา)", "en": "Box Drawings Down Heavy and Right Light" } },
    { "api": "U+250F", "text": "┏", "name": { "th": "มุมบนซ้าย (หนา)", "en": "Box Drawings Heavy Down and Right" } },
    { "api": "U+2510", "text": "┐", "name": { "th": "มุมบนขวา (บาง)", "en": "Box Drawings Light Down and Left" } },
    { "api": "U+2511", "text": "┑", "name": { "th": "มุมบนขวา (นอนหนา)", "en": "Box Drawings Down Light and Left Heavy" } },
    { "api": "U+2512", "text": "┒", "name": { "th": "มุมบนขวา (ตั้งหนา)", "en": "Box Drawings Down Heavy and Left Light" } },
    { "api": "U+2513", "text": "┓", "name": { "th": "มุมบนขวา (หนา)", "en": "Box Drawings Heavy Down and Left" } },
    { "api": "U+2514", "text": "└", "name": { "th": "มุมล่างซ้าย (บาง)", "en": "Box Drawings Light Up and Right" } },
    { "api": "U+2515", "text": "┕", "name": { "th": "มุมล่างซ้าย (นอนหนา)", "en": "Box Drawings Up Light and Right Heavy" } },
    { "api": "U+2516", "text": "┖", "name": { "th": "มุมล่างซ้าย (ตั้งหนา)", "en": "Box Drawings Up Heavy and Right Light" } },
    { "api": "U+2517", "text": "┗", "name": { "th": "มุมล่างซ้าย (หนา)", "en": "Box Drawings Heavy Up and Right" } },
    { "api": "U+2518", "text": "┘", "name": { "th": "มุมล่างขวา (บาง)", "en": "Box Drawings Light Up and Left" } },
    { "api": "U+2519", "text": "┙", "name": { "th": "มุมล่างขวา (นอนหนา)", "en": "Box Drawings Up Light and Left Heavy" } },
    { "api": "U+251A", "text": "┚", "name": { "th": "มุมล่างขวา (ตั้งหนา)", "en": "Box Drawings Up Heavy and Left Light" } },
    { "api": "U+251B", "text": "┛", "name": { "th": "มุมล่างขวา (หนา)", "en": "Box Drawings Heavy Up and Left" } },
    { "api": "U+251C", "text": "├", "name": { "th": "แยกขวา (บาง)", "en": "Box Drawings Light Vertical and Right" } },
    { "api": "U+251D", "text": "┝", "name": { "th": "แยกขวา (นอนหนา)", "en": "Box Drawings Vertical Light and Right Heavy" } },
    { "api": "U+2520", "text": "┠", "name": { "th": "แยกขวา (ตั้งหนา)", "en": "Box Drawings Vertical Heavy and Right Light" } },
    { "api": "U+2523", "text": "┣", "name": { "th": "แยกขวา (หนา)", "en": "Box Drawings Heavy Vertical and Right" } },
    { "api": "U+2524", "text": "┤", "name": { "th": "แยกซ้าย (บาง)", "en": "Box Drawings Light Vertical and Left" } },
    { "api": "U+2525", "text": "┥", "name": { "th": "แยกซ้าย (นอนหนา)", "en": "Box Drawings Vertical Light and Left Heavy" } },
    { "api": "U+2528", "text": "┨", "name": { "th": "แยกซ้าย (ตั้งหนา)", "en": "Box Drawings Vertical Heavy and Left Light" } },
    { "api": "U+252B", "text": "┫", "name": { "th": "แยกซ้าย (หนา)", "en": "Box Drawings Heavy Vertical and Left" } },
    { "api": "U+252C", "text": "┬", "name": { "th": "แยกลง (บาง)", "en": "Box Drawings Light Down and Horizontal" } },
    { "api": "U+252F", "text": "┯", "name": { "th": "แยกลง (นอนหนา)", "en": "Box Drawings Down Light and Horizontal Heavy" } },
    { "api": "U+2530", "text": "┰", "name": { "th": "แยกลง (ตั้งหนา)", "en": "Box Drawings Down Heavy and Horizontal Light" } },
    { "api": "U+2533", "text": "┳", "name": { "th": "แยกลง (หนา)", "en": "Box Drawings Heavy Down and Horizontal" } },
    { "api": "U+2534", "text": "┴", "name": { "th": "แยกขึ้น (บาง)", "en": "Box Drawings Light Up and Horizontal" } },
    { "api": "U+2537", "text": "┷", "name": { "th": "แยกขึ้น (นอนหนา)", "en": "Box Drawings Up Light and Horizontal Heavy" } },
    { "api": "U+2538", "text": "┸", "name": { "th": "แยกขึ้น (ตั้งหนา)", "en": "Box Drawings Up Heavy and Horizontal Light" } },
    { "api": "U+253B", "text": "┻", "name": { "th": "แยกขึ้น (หนา)", "en": "Box Drawings Heavy Up and Horizontal" } },
    { "api": "U+253C", "text": "┼", "name": { "th": "กากบาทเส้น (บาง)", "en": "Box Drawings Light Vertical and Horizontal" } },
    { "api": "U+253F", "text": "┿", "name": { "th": "กากบาทเส้น (นอนหนา)", "en": "Box Drawings Vertical Light and Horizontal Heavy" } },
    { "api": "U+2542", "text": "╂", "name": { "th": "กากบาทเส้น (ตั้งหนา)", "en": "Box Drawings Vertical Heavy and Horizontal Light" } },
    { "api": "U+254B", "text": "╋", "name": { "th": "กากบาทเส้น (หนา)", "en": "Box Drawings Heavy Vertical and Horizontal" } },
    { "api": "U+2550", "text": "═", "name": { "th": "เส้นนอนคู่", "en": "Box Drawings Double Horizontal" } },
    { "api": "U+2551", "text": "║", "name": { "th": "เส้นตั้งคู่", "en": "Box Drawings Double Vertical" } },
    { "api": "U+2552", "text": "╒", "name": { "th": "มุมบนซ้าย (นอนคู่)", "en": "Box Drawings Down Single and Right Double" } },
    { "api": "U+2553", "text": "╓", "name": { "th": "มุมบนซ้าย (ตั้งคู่)", "en": "Box Drawings Down Double and Right Single" } },
    { "api": "U+2554", "text": "╔", "name": { "th": "มุมบนซ้าย (คู่)", "en": "Box Drawings Double Down and Right" } },
    { "api": "U+2555", "text": "╕", "name": { "th": "มุมบนขวา (นอนคู่)", "en": "Box Drawings Down Single and Left Double" } },
    { "api": "U+2556", "text": "╖", "name": { "th": "มุมบนขวา (ตั้งคู่)", "en": "Box Drawings Down Double and Left Single" } },
    { "api": "U+2557", "text": "╗", "name": { "th": "มุมบนขวา (คู่)", "en": "Box Drawings Double Down and Left" } },
    { "api": "U+2558", "text": "╘", "name": { "th": "มุมล่างซ้าย (นอนคู่)", "en": "Box Drawings Up Single and Right Double" } },
    { "api": "U+2559", "text": "╙", "name": { "th": "มุมล่างซ้าย (ตั้งคู่)", "en": "Box Drawings Up Double and Right Single" } },
    { "api": "U+255A", "text": "╚", "name": { "th": "มุมล่างซ้าย (คู่)", "en": "Box Drawings Double Up and Right" } },
    { "api": "U+255B", "text": "╛", "name": { "th": "มุมล่างขวา (นอนคู่)", "en": "Box Drawings Up Single and Left Double" } },
    { "api": "U+255C", "text": "╜", "name": { "th": "มุมล่างขวา (ตั้งคู่)", "en": "Box Drawings Up Double and Left Single" } },
    { "api": "U+255D", "text": "╝", "name": { "th": "มุมล่างขวา (คู่)", "en": "Box Drawings Double Up and Left" } },
    { "api": "U+255E", "text": "╞", "name": { "th": "แยกขวา (นอนคู่)", "en": "Box Drawings Vertical Single and Right Double" } },
    { "api": "U+255F", "text": "╟", "name": { "th": "แยกขวา (ตั้งคู่)", "en": "Box Drawings Vertical Double and Right Single" } },
    { "api": "U+2560", "text": "╠", "name": { "th": "แยกขวา (คู่)", "en": "Box Drawings Double Vertical and Right" } },
    { "api": "U+2561", "text": "╡", "name": { "th": "แยกซ้าย (นอนคู่)", "en": "Box Drawings Vertical Single and Left Double" } },
    { "api": "U+2562", "text": "╢", "name": { "th": "แยกซ้าย (ตั้งคู่)", "en": "Box Drawings Vertical Double and Left Single" } },
    { "api": "U+2563", "text": "╣", "name": { "th": "แยกซ้าย (คู่)", "en": "Box Drawings Double Vertical and Left" } },
    { "api": "U+2564", "text": "╤", "name": { "th": "แยกลง (นอนคู่)", "en": "Box Drawings Down Single and Horizontal Double" } },
    { "api": "U+2565", "text": "╥", "name": { "th": "แยกลง (ตั้งคู่)", "en": "Box Drawings Down Double and Horizontal Single" } },
    { "api": "U+2566", "text": "╦", "name": { "th": "แยกลง (คู่)", "en": "Box Drawings Double Down and Horizontal" } },
    { "api": "U+2567", "text": "╧", "name": { "th": "แยกขึ้น (นอนคู่)", "en": "Box Drawings Up Single and Horizontal Double" } },
    { "api": "U+2568", "text": "╨", "name": { "th": "แยกขึ้น (ตั้งคู่)", "en": "Box Drawings Up Double and Horizontal Single" } },
    { "api": "U+2569", "text": "╩", "name": { "th": "แยกขึ้น (คู่)", "en": "Box Drawings Double Up and Horizontal" } },
    { "api": "U+256A", "text": "╪", "name": { "th": "กากบาท (นอนคู่)", "en": "Box Drawings Vertical Single and Horizontal Double" } },
    { "api": "U+256B", "text": "╫", "name": { "th": "กากบาท (ตั้งคู่)", "en": "Box Drawings Vertical Double and Horizontal Single" } },
    { "api": "U+256C", "text": "╬", "name": { "th": "กากบาท (คู่)", "en": "Box Drawings Double Vertical and Horizontal" } },
    { "api": "U+2574", "text": "╴", "name": { "th": "เส้นซ้ายบาง", "en": "Box Drawings Light Left" } },
    { "api": "U+2575", "text": "╵", "name": { "th": "เส้นขึ้นบาง", "en": "Box Drawings Light Up" } },
    { "api": "U+2576", "text": "╶", "name": { "th": "เส้นขวาบาง", "en": "Box Drawings Light Right" } },
    { "api": "U+2577", "text": "╷", "name": { "th": "เส้นลงบาง", "en": "Box Drawings Light Down" } },
    { "api": "U+2578", "text": "╸", "name": { "th": "เส้นซ้ายหนา", "en": "Box Drawings Heavy Left" } },
    { "api": "U+2579", "text": "╹", "name": { "th": "เส้นขึ้นหนา", "en": "Box Drawings Heavy Up" } },
    { "api": "U+257A", "text": "╺", "name": { "th": "เส้นขวาหนา", "en": "Box Drawings Heavy Right" } },
    { "api": "U+257B", "text": "╻", "name": { "th": "เส้นลงหนา", "en": "Box Drawings Heavy Down" } },
    { "api": "U+257C", "text": "╼", "name": { "th": "เส้นนอน (ซ้ายบาง-ขวาหนา)", "en": "Box Drawings Light Left and Heavy Right" } },
    { "api": "U+257D", "text": "╽", "name": { "th": "เส้นตั้ง (บนบาง-ล่างหนา)", "en": "Box Drawings Light Up and Heavy Down" } },
    { "api": "U+257E", "text": "╾", "name": { "th": "เส้นนอน (ซ้ายหนา-ขวาบาง)", "en": "Box Drawings Heavy Left and Light Right" } },
    { "api": "U+257F", "text": "╿", "name": { "th": "เส้นตั้ง (บนหนา-ล่างบาง)", "en": "Box Drawings Heavy Up and Light Down" } },
    { "api": "U+2580", "text": "▀", "name": { "th": "ครึ่งบน", "en": "Upper Half Block" } },
    { "api": "U+2581", "text": "▁", "name": { "th": "หนึ่งในแปดล่าง", "en": "Lower One Eighth Block" } },
    { "api": "U+2582", "text": "▂", "name": { "th": "สองในแปดล่าง", "en": "Lower One Quarter Block" } },
    { "api": "U+2583", "text": "▃", "name": { "th": "สามในแปดล่าง", "en": "Lower Three Eighths Block" } },
    { "api": "U+2584", "text": "▄", "name": { "th": "ครึ่งล่าง", "en": "Lower Half Block" } },
    { "api": "U+2585", "text": "▅", "name": { "th": "ห้าในแปดล่าง", "en": "Lower Five Eighths Block" } },
    { "api": "U+2586", "text": "▆", "name": { "th": "หกในแปดล่าง", "en": "Lower Three Quarters Block" } },
    { "api": "U+2587", "text": "▇", "name": { "th": "เจ็ดในแปดล่าง", "en": "Lower Seven Eighths Block" } },
    { "api": "U+2588", "text": "█", "name": { "th": "บล็อกเต็ม", "en": "Full Block" } },
    { "api": "U+2589", "text": "▉", "name": { "th": "เจ็ดในแปดซ้าย", "en": "Left Seven Eighths Block" } },
    { "api": "U+258A", "text": "▊", "name": { "th": "หกในแปดซ้าย", "en": "Left Three Quarters Block" } },
    { "api": "U+258B", "text": "▋", "name": { "th": "ห้าในแปดซ้าย", "en": "Left Five Eighths Block" } },
    { "api": "U+258C", "text": "▌", "name": { "th": "ครึ่งซ้าย", "en": "Left Half Block" } },
    { "api": "U+258D", "text": "▍", "name": { "th": "สามในแปดซ้าย", "en": "Left Three Eighths Block" } },
    { "api": "U+258E", "text": "▎", "name": { "th": "สองในแปดซ้าย", "en": "Left One Quarter Block" } },
    { "api": "U+258F", "text": "▏", "name": { "th": "หนึ่งในแปดซ้าย", "en": "Left One Eighth Block" } },
    { "api": "U+2590", "text": "▐", "name": { "th": "ครึ่งขวา", "en": "Right Half Block" } },
    { "api": "U+2591", "text": "░", "name": { "th": "เฉดอ่อน", "en": "Light Shade" } },
    { "api": "U+2592", "text": "▒", "name": { "th": "เฉดกลาง", "en": "Medium Shade" } },
    { "api": "U+2593", "text": "▓", "name": { "th": "เฉดเข้ม", "en": "Dark Shade" } },
    { "api": "U+2594", "text": "▔", "name": { "th": "หนึ่งในแปดบน", "en": "Upper One Eighth Block" } },
    { "api": "U+2595", "text": "▕", "name": { "th": "หนึ่งในแปดขวา", "en": "Right One Eighth Block" } }
  ]
}